Workbook

Sheet Cover
B11: Full Valuation Model
B13: Table of Contents:
C15: Outputs
C16: Inputs
C17: Comparative Valuation
C18: DCF Valuation

Sheet Outputs
B8: Dashboard
B10: All figures in INR Crores unless stated | H10: 2024 | I10: =H10 + 1 -> 2025 | J10: =I10 + 1 -> 2026 | K10: =J10 + 1 -> 2027 | L10: =K10 + 1 -> 2028 | M10: =L10 + 1 -> 2029 | N10: =M10 + 1 -> 2030
B12: Model Switch:
B13: =_xlfn.CONCAT("Model Currently Running:", " ", INDEX(Inputs!$B$15:$B$17, Inputs!$F$8), " ", "Scenario") -> Model Currently Running: Base Case Scenario
B15: INCOME STATEMENT
B17: Revenue | H17: ='DCF Valuation'!H13 -> 74537 | I17: ='DCF Valuation'!I13 -> 85498 | J17: ='DCF Valuation'!J13 -> 98322.7 | K17: ='DCF Valuation'!K13 -> 112579.49 | L17: ='DCF Valuation'!L13 -> 128340.62 | M17: ='DCF Valuation'!M13 -> 145987.46 | N17: ='DCF Valuation'!N13 -> 165695.76
B19: EBITDA | H19: ='DCF Valuation'!H18 -> 19774 | I19: ='DCF Valuation'!I18 -> 23555 | J19: ='DCF Valuation'!J18 -> 34412.945 | K19: ='DCF Valuation'!K18 -> 38839.925 | L19: ='DCF Valuation'!L18 -> 43635.811 | M19: ='DCF Valuation'!M18 -> 48905.798 | N19: ='DCF Valuation'!N18 -> 54679.601
B20: EBITDA Margin | H20: =H19/H17 -> 0.26529106 | I20: =I19/I17 -> 0.27550352 | J20: =J19/J17 -> 0.35 | K20: =K19/K17 -> 0.345 | L20: =L19/L17 -> 0.34 | M20: =M19/M17 -> 0.335 | N20: =N19/N17 -> 0.33
B22: Net Income | H22: ='DCF Valuation'!H30 -> 10105 | I22: ='DCF Valuation'!I30 -> 12599 | J22: ='DCF Valuation'!J30 -> 15771.67 | K22: ='DCF Valuation'!K30 -> 18423.697 | L22: ='DCF Valuation'!L30 -> 21254.885 | M22: ='DCF Valuation'!M30 -> 24331.211 | N22: ='DCF Valuation'!N30 -> 27662.702
B23: Net Income Margin | H23: =H22/H17 -> 0.13557025 | I23: =I22/I17 -> 0.14736017 | J23: =J22/J17 -> 0.16040721 | K23: =K22/K17 -> 0.16365056 | L23: =L22/L17 -> 0.16561308 | M23: =M22/M17 -> 0.16666645 | N23: =N22/N17 -> 0.16694876
B26: CASH FLOW STATEMENT
B28: Cash From Operating Activities | J28: ='DCF Valuation'!J48 -> 24714.56 | K28: ='DCF Valuation'!K48 -> 28519.347 | L28: ='DCF Valuation'!L48 -> 32279.661 | M28: ='DCF Valuation'!M48 -> 36408.147 | N28: ='DCF Valuation'!N48 -> 40939.29
B29: Cash From Investing Activities | J29: ='DCF Valuation'!J57 -> -14812.316 | K29: ='DCF Valuation'!K57 -> -16728.552 | L29: ='DCF Valuation'!L57 -> -18804.267 | M29: ='DCF Valuation'!M57 -> -21237.406 | N29: ='DCF Valuation'!N57 -> -23930.667
B30: Cash From Financing Activities | J30: ='DCF Valuation'!J66 -> -2036.0587 | K30: ='DCF Valuation'!K66 -> -2263.1091 | L30: ='DCF Valuation'!L66 -> -2507.2852 | M30: ='DCF Valuation'!M66 -> -2754.2874 | N30: ='DCF Valuation'!N66 -> -3020.3655
B31: Change in Cash | J31: =SUM(J28:J30) -> 7866.1852 | K31: =SUM(K28:K30) -> 9527.6859 | L31: =SUM(L28:L30) -> 10968.11 | M31: =SUM(M28:M30) -> 12416.453 | N31: =SUM(N28:N30) -> 13988.257
B33: Unlevered Free Cash Flows | J33: ='DCF Valuation'!J269 -> 21860.399 | K33: ='DCF Valuation'!K269 -> 24918.091 | L33: ='DCF Valuation'!L269 -> 27717.493 | M33: ='DCF Valuation'!M269 -> 30827.871 | N33: ='DCF Valuation'!N269 -> 34220.184
B54: DCF Valuation | K54: Inputs Taken
C56: Scenario Analysis | E56: Enterprise Value | G56: Equity Value | K56: Total Shares Outstanding | N56: (millions) | O56: =Inputs!K60 -> 143.78466
C57: Best Case | E57: =Inputs!O16 -> 365397.34 | G57: =E57/$O$56 -> 2541.2819 | K57: WACC | O57: =Inputs!F103 -> 0.11768508
C58: Base Case | E58: =Inputs!O17 -> 315962.18 | G58: =E58/$O$56 -> 2197.468 | K58: Terminal Growth Rate | O58: ='DCF Valuation'!E272 -> 0.03
C59: Worst Case | E59: =Inputs!O18 -> 269645.5 | G59: =E59/$O$56 -> 1875.3426 | K59: Net Debt | O59: =-'DCF Valuation'!F286 -> 22376
K60: Current Share Price | O60: =Inputs!K62 -> 8075
B63: Sensitivity Analysis
B65: Enterprise Value | J65: Equity Value
F67: Terminal Growth | N67: Terminal Growth
D68: 0.025 | E68: 0.0275 | F68: 0.03 | G68: 0.0325 | H68: 0.035 | L68: 0.025 | M68: 0.0275 | N68: 0.03 | O68: 0.0325 | P68: 0.035
B69: WACC | C69: 0.11576491 | D69: ='DCF Valuation'!F295 -> 311946.46 | E69: ='DCF Valuation'!G295 -> 317438.89 | F69: ='DCF Valuation'!H295 -> 323254.17 | G69: ='DCF Valuation'!I295 -> 329421.38 | H69: ='DCF Valuation'!J295 -> 335973.16 | J69: WACC | K69: 0.11576491 | L69: =D69-$O$59 -> 289570.46 | M69: =E69-$O$59 -> 295062.89 | N69: =F69-$O$59 -> 300878.17 | O69: =G69-$O$59 -> 307045.38 | P69: =H69-$O$59 -> 313597.16
C70: 0.11676491 | D70: ='DCF Valuation'!F296 -> 308421.75 | E70: ='DCF Valuation'!G296 -> 313763.75 | F70: ='DCF Valuation'!H296 -> 319416.2 | G70: ='DCF Valuation'!I296 -> 325406.73 | H70: ='DCF Valuation'!J296 -> 331766.31 | K70: 0.11676491 | L70: =D70-$O$59 -> 286045.75 | M70: =E70-$O$59 -> 291387.75 | N70: =F70-$O$59 -> 297040.2 | O70: =G70-$O$59 -> 303030.73 | P70: =H70-$O$59 -> 309390.31
C71: 0.11776491 | D71: ='DCF Valuation'!F297 -> 304973.38 | E71: ='DCF Valuation'!G297 -> 310170.35 | F71: ='DCF Valuation'!H297 -> 315665.97 | G71: ='DCF Valuation'!I297 -> 321486.49 | H71: ='DCF Valuation'!J297 -> 327661.33 | K71: 0.11776491 | L71: =D71-$O$59 -> 282597.38 | M71: =E71-$O$59 -> 287794.35 | N71: =F71-$O$59 -> 293289.97 | O71: =G71-$O$59 -> 299110.49 | P71: =H71-$O$59 -> 305285.33
C72: 0.11876491 | D72: ='DCF Valuation'!F298 -> 301598.91 | E72: ='DCF Valuation'!G298 -> 306656.02 | F72: ='DCF Valuation'!H298 -> 312000.52 | G72: ='DCF Valuation'!I298 -> 317657.38 | H72: ='DCF Valuation'!J298 -> 323654.55 | K72: 0.11876491 | L72: =D72-$O$59 -> 279222.91 | M72: =E72-$O$59 -> 284280.02 | N72: =F72-$O$59 -> 289624.52 | O72: =G72-$O$59 -> 295281.38 | P72: =H72-$O$59 -> 301278.55
C73: 0.11976491 | D73: ='DCF Valuation'!F299 -> 298296 | E73: ='DCF Valuation'!G299 -> 303218.17 | F73: ='DCF Valuation'!H299 -> 308417 | G73: ='DCF Valuation'!I299 -> 313916.26 | H73: ='DCF Valuation'!J299 -> 319742.51 | K73: 0.11976491 | L73: =D73-$O$59 -> 275920 | M73: =E73-$O$59 -> 280842.17 | N73: =F73-$O$59 -> 286041 | O73: =G73-$O$59 -> 291540.26 | P73: =H73-$O$59 -> 297366.51
B77: Equity per Share | J77: Premium/(Discount)
F79: Terminal Growth | N79: Terminal Growth
D80: 0.025 | E80: 0.0275 | F80: 0.03 | G80: 0.0325 | H80: 0.035 | L80: 0.025 | M80: 0.0275 | N80: 0.03 | O80: 0.0325 | P80: 0.035
B81: WACC | C81: 0.11576491 | D81: =L69/$O$56 -> 2013.9177 | E81: =M69/$O$56 -> 2052.1166 | F81: =N69/$O$56 -> 2092.561 | G81: =O69/$O$56 -> 2135.453 | H81: =P69/$O$56 -> 2181.0197 | J81: WACC | K81: 0.11576491 | L81: =D81/($O$60-1) -> 0.24943246 | M81: =E81/($O$60-1) -> 0.25416357 | N81: =F81/($O$60-1) -> 0.25917278 | O81: =G81/($O$60-1) -> 0.26448514 | P81: =H81/($O$60-1) -> 0.27012877
C82: 0.11676491 | D82: =L70/$O$56 -> 1989.4039 | E82: =M70/$O$56 -> 2026.5566 | F82: =N70/$O$56 -> 2065.8686 | G82: =O70/$O$56 -> 2107.5317 | H82: =P70/$O$56 -> 2151.7617 | K82: 0.11676491 | L82: =D82/($O$60-1) -> 0.24639632 | M82: =E82/($O$60-1) -> 0.25099785 | N82: =F82/($O$60-1) -> 0.2558668 | O82: =G82/($O$60-1) -> 0.26102697 | P82: =H82/($O$60-1) -> 0.26650504
C83: 0.11776491 | D83: =L71/$O$56 -> 1965.421 | E83: =M71/$O$56 -> 2001.5651 | F83: =N71/$O$56 -> 2039.7863 | G83: =O71/$O$56 -> 2080.2671 | H83: =P71/$O$56 -> 2123.2121 | K83: 0.11776491 | L83: =D83/($O$60-1) -> 0.24342594 | M83: =E83/($O$60-1) -> 0.24790254 | N83: =F83/($O$60-1) -> 0.2526364 | O83: =G83/($O$60-1) -> 0.25765012 | P83: =H83/($O$60-1) -> 0.26296905
C84: 0.11876491 | D84: =L72/$O$56 -> 1941.9521 | E84: =M72/$O$56 -> 1977.1235 | F84: =N72/$O$56 -> 2014.2936 | G84: =O72/$O$56 -> 2053.6362 | H84: =P72/$O$56 -> 2095.3456 | K84: 0.11876491 | L84: =D84/($O$60-1) -> 0.24051921 | M84: =E84/($O$60-1) -> 0.24487533 | N84: =F84/($O$60-1) -> 0.24947902 | O84: =G84/($O$60-1) -> 0.25435177 | P84: =H84/($O$60-1) -> 0.25951766
C85: 0.11976491 | D85: =L73/$O$56 -> 1918.9808 | E85: =M73/$O$56 -> 1953.2137 | F85: =N73/$O$56 -> 1989.3708 | G85: =O73/$O$56 -> 2027.6173 | H85: =P73/$O$56 -> 2068.138 | K85: 0.11976491 | L85: =D85/($O$60-1) -> 0.23767411 | M85: =E85/($O$60-1) -> 0.24191401 | N85: =F85/($O$60-1) -> 0.24639222 | O85: =G85/($O$60-1) -> 0.25112922 | P85: =H85/($O$60-1) -> 0.25614788
B88: Valuation Summary
E90: Low | F90: Delta | G90: High | H90: Mid
B91: Comparable Trading Analysis | E91: ='Comps Table'!G33 -> 315962.18 | F91: =G91-E91 -> 967516.75 | G91: ='Comps Table'!G32 -> 1283478.9 | H91: ='Comps Table'!G31 -> 864393.96
B92: DCF Valuation Analysis | E92: =D73 -> 298296 | F92: =G92-E92 -> 37677.167 | G92: =H69 -> 335973.16 | H92: =F71 -> 315665.97

Sheet Inputs
B8: Assumptions and Drivers | F8: 2
B10: All Figures in INR millions unless stated | H10: 2026 | I10: =H10+1 -> 2027 | J10: =I10+1 -> 2028 | K10: =J10+1 -> 2029 | L10: =K10+1 -> 2030
B11: =_xlfn.CONCAT("Model Currently Running:", " ", INDEX(Inputs!$B$15:$B$17, Inputs!$F$8), " ", "Scenario") -> Model Currently Running: Base Case Scenario
B13: Revenue Growth | H13: {=INDEX(H15:H17, $F$8)} -> 0.15 | I13: {=INDEX(I15:I17, $F$8)} -> 0.145 | J13: {=INDEX(J15:J17, $F$8)} -> 0.14 | K13: {=INDEX(K15:K17, $F$8)} -> 0.1375 | L13: {=INDEX(L15:L17, $F$8)} -> 0.135 | O13: Enterprise
O14: Value
B15: Best Case | H15: =H16 + 0.01 -> 0.16 | I15: =I16 + 0.01 -> 0.155 | J15: =J16 + 0.01 -> 0.15 | K15: =K16 + 0.01 -> 0.1475 | L15: =L16 + 0.01 -> 0.145 | O15: ='DCF Valuation'!F285 -> 315962.18
B16: Base Case | H16: 0.15 | I16: =H16-0.005 -> 0.145 | J16: =I16-0.005 -> 0.14 | K16: =J16-0.0025 -> 0.1375 | L16: =K16-0.0025 -> 0.135 | N16: 1 | O16: 365397.34
B17: Worst Case | H17: =H16-0.01 -> 0.14 | I17: =I16-0.01 -> 0.135 | J17: =J16-0.01 -> 0.13 | K17: =K16-0.01 -> 0.1275 | L17: =L16-0.01 -> 0.125 | N17: 2 | O17: 315962.18
N18: 3 | O18: 269645.5
B20: COGS | F20: (as % of revenue) | H20: {=INDEX(H22:H24, $F$8)} -> 0.25 | I20: {=INDEX(I22:I24, $F$8)} -> 0.2525 | J20: {=INDEX(J22:J24, $F$8)} -> 0.255 | K20: {=INDEX(K22:K24, $F$8)} -> 0.2575 | L20: {=INDEX(L22:L24, $F$8)} -> 0.26
B22: Best Case | H22: =H23-0.01 -> 0.24 | I22: =I23-0.01 -> 0.2425 | J22: =J23-0.01 -> 0.245 | K22: =K23-0.01 -> 0.2475 | L22: =L23-0.01 -> 0.25
B23: Base Case | H23: 0.25 | I23: =H23 +0.0025 -> 0.2525 | J23: =I23 +0.0025 -> 0.255 | K23: =J23 +0.0025 -> 0.2575 | L23: =K23 +0.0025 -> 0.26
B24: Worst Case | H24: =H23+0.01 -> 0.26 | I24: =I23+0.01 -> 0.2625 | J24: =J23+0.01 -> 0.265 | K24: =K23+0.01 -> 0.2675 | L24: =L23+0.01 -> 0.27
B27: SG&A | F27: (as % of revenue) | H27: {=INDEX(H29:H31, $F$8)} -> 0.4 | I27: {=INDEX(I29:I31, $F$8)} -> 0.4025 | J27: {=INDEX(J29:J31, $F$8)} -> 0.405 | K27: {=INDEX(K29:K31, $F$8)} -> 0.4075 | L27: {=INDEX(L29:L31, $F$8)} -> 0.41
B29: Best Case | H29: =H30-0.01 -> 0.39 | I29: =I30-0.01 -> 0.3925 | J29: =J30-0.01 -> 0.395 | K29: =K30-0.01 -> 0.3975 | L29: =L30-0.01 -> 0.4
B30: Base Case | H30: 0.4 | I30: =H30+0.0025 -> 0.4025 | J30: =I30+0.0025 -> 0.405 | K30: =J30+0.0025 -> 0.4075 | L30: =K30+0.0025 -> 0.41
B31: Worst Case | H31: =H30+0.01 -> 0.41 | I31: =I30+0.01 -> 0.4125 | J31: =J30+0.01 -> 0.415 | K31: =K30+0.01 -> 0.4175 | L31: =L30+0.01 -> 0.42
B34: Capital Expenditure | F34: (as % of revenue) | H34: {=INDEX(H36:H38, $F$8)} -> 0.08 | I34: {=INDEX(I36:I38, $F$8)} -> 0.08 | J34: {=INDEX(J36:J38, $F$8)} -> 0.08 | K34: {=INDEX(K36:K38, $F$8)} -> 0.08 | L34: {=INDEX(L36:L38, $F$8)} -> 0.08
B36: Best Case | H36: =H37-0.01 -> 0.07 | I36: =I37-0.01 -> 0.07 | J36: =J37-0.01 -> 0.07 | K36: =K37-0.01 -> 0.07 | L36: =L37-0.01 -> 0.07
B37: Base Case | H37: 0.08 | I37: =H37 -> 0.08 | J37: =I37 -> 0.08 | K37: =J37 -> 0.08 | L37: =K37 -> 0.08
B38: Worst Case | H38: =H37+0.01 -> 0.09 | I38: =I37+0.01 -> 0.09 | J38: =J37+0.01 -> 0.09 | K38: =K37+0.01 -> 0.09 | L38: =L37+0.01 -> 0.09
B41: Amounts Per Day
B43: Accounts Recievable | H43: 35 | I43: 35 | J43: 35 | K43: 35 | L43: 35
B44: Inventory | H44: 20 | I44: =H44 -> 20 | J44: =I44 -> 20 | K44: =J44 -> 20 | L44: =K44 -> 20
B45: Accounts Payable | H45: =135 -> 135 | I45: =H45 -> 135 | J45: =I45 -> 135 | K45: =J45 -> 135 | L45: =K45 -> 135
B48: Other Inputs
B50: All Figures in INR millions unless stated | H50: 2026 | I50: =H50+1 -> 2027 | J50: =I50+1 -> 2028 | K50: =J50+1 -> 2029 | L50: =K50+1 -> 2030
B52: Other Annual Inputs
B54: Inflation Rate | H54: 0.034 | I54: =H54 -> 0.034 | J54: =I54-0.001 -> 0.033 | K54: =J54-0.001 -> 0.032 | L54: =K54-0.001 -> 0.031
B55: Term Debt | E55: Increase / (Decrease) | H55: -1000 | I55: -1000 | J55: -1000 | K55: -1000 | L55: -1000
B56: Common Equity | E56: Increase / (Decrease) | H56: 0 | I56: 0 | J56: 0 | K56: 0 | L56: 0
B57: Dividend Payout Ratio | H57: 0.125 | I57: 0.125 | J57: 0.125 | K57: 0.125 | L57: 0.125
B60: Tax Rate | D60: 0.28 | H60: Shares Outstanding | K60: 143.78466
B61: Interest Rate | D61: 0.1 | H61: Terminal Growth Rate | K61: 0.03
H62: Current Share Price | K62: 8075
B64: Weighted Average Cost of Capital (WACC)
H66: Average | I66: Debt/ | J66: Debt/ | K66: Levered | L66: Unlevered
B67: Name | D67: Region | F67: Debt | G67: Equity | H67: Tax Rate | I67: Equity | J67: Capital | K67: Beta | L67: Beta
B69: Max Healthcare | D69: India | F69: 3275.02 | G69: 103012.98 | H69: 0.1382 | I69: =F69/G69 -> 0.031792304 | J69: =F69/(F69+G69) -> 0.030812698 | K69: 0.13 | L69: =K69/(1+(1-H69)*I69) -> 0.12653317
B70: Fortis Heathcare | D70: India | F70: 3194 | G70: 72627 | H70: 0.2951 | I70: =F70/G70 -> 0.043978135 | J70: =F70/(F70+G70) -> 0.042125533 | K70: 0.7 | L70: =K70/(1+(1-H70)*I70) -> 0.67895235
B71: Aster DM Health | D71: India | F71: 2219 | G71: 39102 | H71: 0.2503 | I71: =F71/G71 -> 0.056749015 | J71: =F71/(F71+G71) -> 0.053701508 | K71: 0.3 | L71: =K71/(1+(1-H71)*I71) -> 0.28775744
B72: Narayana Hrudaya | D72: India | F72: 2340.22 | G72: 38045.86 | H72: 0.1613 | I72: =F72/G72 -> 0.061510503 | J72: =F72/(F72+G72) -> 0.057946203 | K72: 0.16 | L72: =K72/(1+(1-H72)*I72) -> 0.15215072
B73: Global Health | D73: India | F73: 1090.05 | G73: 33310.77 | H73: 0.2251 | I73: =F73/G73 -> 0.032723651 | J73: =F73/(F73+G73) -> 0.031686745 | K73: 0.17 | L73: =K73/(1+(1-H73)*I73) -> 0.16579582
G75: Average | H75: =AVERAGE(H69:H73) -> 0.214 | I75: =AVERAGE(I69:I73) -> 0.045350722 | J75: =AVERAGE(J69:J73) -> 0.043254537 | K75: =AVERAGE(K69:K73) -> 0.292 | L75: =AVERAGE(L69:L73) -> 0.2822379
G76: Median | H76: =MEDIAN(H69:H73) -> 0.2251 | I76: =MEDIAN(I69:I73) -> 0.043978135 | J76: =MEDIAN(J69:J73) -> 0.042125533 | K76: =MEDIAN(K69:K73) -> 0.17 | L76: =MEDIAN(L69:L73) -> 0.16579582
B79: Risk Premium for Equity | H79: Cost of Equity
B81: Market Risk Premium | F81: 0.0708 | H81: Risk Free Rate | L81: 0.0704
B82: Average Unlevered Beta | F82: =L75 -> 0.2822379 | H82: Equity Risk Premium | L82: =F84 -> 0.020427413
B83: Levered Beta | F83: =F82*(1+(1-L90)*F94) -> 0.28852278 | H83: Country Risk Premium | L83: 0.0285
B84: Equity Risk Premium | F84: =F81*F83 -> 0.020427413 | H84: Cost of Equity | L84: =SUM(L81:L83) -> 0.11932741
B87: Capital Structure | H87: Cost of Debt
E89: Current | F89: Target | H89: Pre-Tax Cost of Debt | L89: =-'DCF Valuation'!I25/'DCF Valuation'!I107 -> 0.089698768
B90: Total Debt | D90: ='DCF Valuation'!I107 -> 28317 | E90: =D90/D92 -> 0.028905959 | F90: 0.03 | H90: Tax Rate | L90: =D60 -> 0.28
B91: Market Cap | D91: 951308 | E91: =1-E90 -> 0.97109404 | F91: =1-F90 -> 0.97 | H91: After-Tax Cost of Debt | L91: =L89*(1-L90) -> 0.064583113
B92: Total Cap | D92: =SUM(D90:D91) -> 979625 | E92: =SUM(E90:E91) -> 1 | F92: =SUM(F90:F91) -> 1
B94: Debt/Equity | E94: =E90/E91 -> 0.029766385 | F94: =F90/F91 -> 0.030927835
B97: Weighted Average Cost of Capital
E99: Weight | F99: Cost
B100: Debt Capital | E100: =F90 -> 0.03 | F100: =L91 -> 0.064583113
B101: Equity Capital | E101: =F91 -> 0.97 | F101: =L84 -> 0.11932741
B103: Weighted Average Cost of Capital | F103: =SUMPRODUCT(E100:E101, F100:F101) -> 0.11768508

Sheet Comps Table
B8: Comprative Trading Analysis
B10: All figures in INR Millions unless stated
F12: Share | G12: Enterprise | I12: EV/ | J12: EBITDA
B13: Peer Companies | F13: Price | G13: Value | H13: EBITDA | I13: EBITDA | J13: Growth | K13: EPS | L13: P/E
F14: (inr/share) | J14: (3 Years)
B15: Apollo Hospitals | F15: =Inputs!K62 -> 8075 | G15: ='DCF Valuation'!F285 -> 315962.18 | H15: ='DCF Valuation'!I18 -> 23555 | I15: =G15/H15 -> 13.413805 | J15: 0.235 | K15: 135.04 | L15: =F15/K15 -> 59.797097
B16: Max Healthcare | F16: 1100 | G16: 1091973.3 | H16: 20040.4 | I16: =G16/H16 -> 54.488598 | J16: 0.2315 | K16: 14.6 | L16: =F16/K16 -> 75.342466
B17: Fortis Heathcare | F17: 979 | G17: 763732 | H17: 16626.7 | I17: =G17/H17 -> 45.93407 | J17: 0.1418 | K17: 12.71 | L17: =F17/K17 -> 77.025964
B18: Aster DM Health | F18: 762 | G18: 403207.2 | H18: 9896.3 | I18: =G18/H18 -> 40.743227 | J18: 0.27 | K18: 7.49 | L18: =F18/K18 -> 101.73565
B19: Narayana Hrudaya | F19: 1916 | G19: 408572.1 | H19: 13747.5 | I19: =G19/H19 -> 29.719738 | J19: 0.2534 | K19: 38.12 | L19: =F19/K19 -> 50.262329
B20: Global Health | F20: 1238 | G20: 332280.3 | H20: 10176.9 | I20: =G20/H20 -> 32.650444 | J20: 0.1404 | K20: 20.7 | L20: =F20/K20 -> 59.806763
B23: Target Company Valuation
B25: All figures in INR Millions unless stated
G27: Enterprise | I27: EV/ | J27: EBITDA
B28: Target Company Valuation | G28: Value | H28: EBITDA | I28: EBITDA | J28: Growth
J29: (3 Years)
B30: Average | G30: =H30*I30 -> 851709.08 | H30: =H15 -> 23555 | I30: =AVERAGE(I15:I20) -> 36.158314 | J30: =J15 -> 0.235
B31: Median | G31: =H31*I31 -> 864393.96 | H31: =H30 -> 23555 | I31: =MEDIAN(I15:I20) -> 36.696835 | J31: =J30 -> 0.235
B32: Maximum | G32: =H32*I32 -> 1283478.9 | H32: =H31 -> 23555 | I32: =MAX(I15:I20) -> 54.488598 | J32: =J31 -> 0.235
B33: Minimum | G33: =H33*I33 -> 315962.18 | H33: =H32 -> 23555 | I33: =MIN(I15:I20) -> 13.413805 | J33: =J32 -> 0.235

Sheet DCF Valuation
B8: Income Statement
B10: All figures in INR millions unless stated | H10: 2024 | I10: =H10 + 1 -> 2025 | J10: =I10 + 1 -> 2026 | K10: =J10 + 1 -> 2027 | L10: =K10 + 1 -> 2028 | M10: =L10 + 1 -> 2029 | N10: =M10 + 1 -> 2030
B11: =_xlfn.CONCAT("Model Currently Running:", " ", INDEX(Inputs!$B$15:$B$17, Inputs!$F$8), " ", "Scenario") -> Model Currently Running: Base Case Scenario
B13: Revenue | H13: 74537 | I13: 85498 | J13: =I13*(1+Inputs!H13) -> 98322.7 | K13: =J13*(1+Inputs!I13) -> 112579.49 | L13: =K13*(1+Inputs!J13) -> 128340.62 | M13: =L13*(1+Inputs!K13) -> 145987.46 | N13: =M13*(1+Inputs!L13) -> 165695.76
B14: COGS | H14: -19990 | I14: -22848 | J14: =-J13 * Inputs!H20 -> -24580.675 | K14: =-K13 * Inputs!I20 -> -28426.322 | L14: =-L13 * Inputs!J20 -> -32726.858 | M14: =-M13 * Inputs!K20 -> -37591.77 | N14: =-N13 * Inputs!L20 -> -43080.898
B15: Gross Profit | H15: =SUM(H13:H14) -> 54547 | I15: =SUM(I13:I14) -> 62650 | J15: =SUM(J13:J14) -> 73742.025 | K15: =SUM(K13:K14) -> 84153.17 | L15: =SUM(L13:L14) -> 95613.762 | M15: =SUM(M13:M14) -> 108395.69 | N15: =SUM(N13:N14) -> 122614.86
B17: SG&A | H17: =-(14252+20521) -> -34773 | I17: =-(15968+23127) -> -39095 | J17: =-J13 * Inputs!H27 -> -39329.08 | K17: =-K13 * Inputs!I27 -> -45313.245 | L17: =-L13 * Inputs!J27 -> -51977.951 | M17: =-M13 * Inputs!K27 -> -59489.888 | N17: =-N13 * Inputs!L27 -> -67935.262
B18: EBITDA | H18: =SUM(H15, H17) -> 19774 | I18: =SUM(I15, I17) -> 23555 | J18: =SUM(J15, J17) -> 34412.945 | K18: =SUM(K15, K17) -> 38839.925 | L18: =SUM(L15, L17) -> 43635.811 | M18: =SUM(M15, M17) -> 48905.798 | N18: =SUM(N15, N17) -> 54679.601
B20: Depreciation and Amortization | H20: -3990 | I20: -4494 | J20: =-J195 -> -9726.1479 | K20: =-K195 -> -10569.757 | L20: =-L195 -> -11533.437 | M20: =-M195 -> -12630.749 | N20: =-N195 -> -13877.482
B21: EBIT | H21: =SUM(H18, H20) -> 15784 | I21: =SUM(I18, I20) -> 19061 | J21: =SUM(J18, J20) -> 24686.797 | K21: =SUM(K18, K20) -> 28270.168 | L21: =SUM(L18, L20) -> 32102.374 | M21: =SUM(M18, M20) -> 36275.048 | N21: =SUM(N18, N20) -> 40802.119
B23: Exceptional Items | H23: 0 | I23: 0 | J23: =I23 -> 0 | K23: =J23 -> 0 | L23: =K23 -> 0 | M23: =L23 -> 0 | N23: =M23 -> 0
B24: Interest Income | H24: 0 | I24: 0 | J24: =I24 -> 0 | K24: =J24 -> 0 | L24: =K24 -> 0 | M24: =L24 -> 0 | N24: =M24 -> 0
B25: Interest Expense | H25: -2498 | I25: =-2540 -> -2540 | J25: =-J216 -> -2781.7 | K25: =-K216 -> -2681.7 | L25: =-L216 -> -2581.7 | M25: =-M216 -> -2481.7 | N25: =-N216 -> -2381.7
B26: EBT | H26: =SUM(H21, H23:H25) -> 13286 | I26: =SUM(I21, I23:I25) -> 16521 | J26: =SUM(J21, J23:J25) -> 21905.097 | K26: =SUM(K21, K23:K25) -> 25588.468 | L26: =SUM(L21, L23:L25) -> 29520.674 | M26: =SUM(M21, M23:M25) -> 33793.348 | N26: =SUM(N21, N23:N25) -> 38420.419
B28: Provision for Taxes | H28: =-3181 -> -3181 | I28: =-3922 -> -3922 | J28: =-J26 * Inputs!$D$60 -> -6133.4272 | K28: =-K26 * Inputs!$D$60 -> -7164.771 | L28: =-L26 * Inputs!$D$60 -> -8265.7886 | M28: =-M26 * Inputs!$D$60 -> -9462.1375 | N28: =-N26 * Inputs!$D$60 -> -10757.717
B30: Net Income | H30: =SUM(H26, H28) -> 10105 | I30: =SUM(I26, I28) -> 12599 | J30: =SUM(J26, J28) -> 15771.67 | K30: =SUM(K26, K28) -> 18423.697 | L30: =SUM(L26, L28) -> 21254.885 | M30: =SUM(M26, M28) -> 24331.211 | N30: =SUM(N26, N28) -> 27662.702
B33: Cash Flow Statement
B35: All Figures in INR millions unless stated | I35: 2025 | J35: =I35 + 1 -> 2026 | K35: =J35 + 1 -> 2027 | L35: =K35 + 1 -> 2028 | M35: =L35 + 1 -> 2029 | N35: =M35 + 1 -> 2030
B36: =_xlfn.CONCAT("Model Currently Running:", " ", INDEX(Inputs!$B$15:$B$17, Inputs!$F$8), " ", "Scenario") -> Model Currently Running: Base Case Scenario
B38: CASH FROM OPERATIONS
B40: Net Income | J40: =J30 -> 15771.67 | K40: =K30 -> 18423.697 | L40: =L30 -> 21254.885 | M40: =M30 -> 24331.211 | N40: =N30 -> 27662.702
B41: Depreciation & Amortization | J41: =-J20 -> 9726.1479 | K41: =-K20 -> 10569.757 | L41: =-L20 -> 11533.437 | M41: =-M20 -> 12630.749 | N41: =-N20 -> 13877.482
B42: Change in Accounts Recievable | J42: =-(J84-I84) -> -1280.2041 | K42: =-(K84-J84) -> -1367.0896 | L42: =-(L84-K84) -> -1511.3411 | M42: =-(M84-L84) -> -1692.1623 | N42: =-(N84-M84) -> -1889.8376
B43: Change in Inventory | J43: =-(J85-I85) -> -80.886301 | K43: =-(K85-J85) -> -210.72036 | L43: =-(L85-K85) -> -235.64584 | M43: =-(M85-L85) -> -266.5705 | N43: =-(N85-M85) -> -300.77416
B44: Change in Other Current Assets | J44: =-(J86-I86) -> -826.8 | K44: =-(K86-J86) -> -919.126 | L44: =-(L86-K86) -> -1016.1096 | M44: =-(M86-L86) -> -1137.6799 | N44: =-(N86-M86) -> -1270.5816
B45: Change in Accounts Payable | J45: =J101-I101 -> 864.48253 | K45: =K101-J101 -> 1422.3624 | L45: =L101-K101 -> 1590.6094 | M45: =M101-L101 -> 1799.3509 | N45: =N101-M101 -> 2030.2255
B46: Change in Other Payables | J46: 0 | K46: 0 | L46: 0 | M46: 0 | N46: 0
B47: Change in Other Current Liabilities | J47: =J103-I103 -> 540.15 | K47: =K103-J103 -> 600.46675 | L47: =L103-K103 -> 663.82634 | M47: =M103-L103 -> 743.24843 | N47: =N103-M103 -> 830.07336
B48: Cash from Operating Activities | J48: =SUM(J40:J47) -> 24714.56 | K48: =SUM(K40:K47) -> 28519.347 | L48: =SUM(L40:L47) -> 32279.661 | M48: =SUM(M40:M47) -> 36408.147 | N48: =SUM(N40:N47) -> 40939.29
B50: CASH FROM INVESTING
B52: Capital Expenditure | J52: =-J158 -> -7865.816 | K52: =-K158 -> -9006.3593 | L52: =-L158 -> -10267.25 | M52: =-M158 -> -11678.996 | N52: =-N158 -> -13255.661
B53: Change in Intangible Assets | J53: =-(J91-I91) -> 0 | K53: =-(K91-J91) -> 0 | L53: =-(L91-K91) -> 0 | M53: =-(M91-L91) -> 0 | N53: =-(N91-M91) -> 0
B54: Change in Short Term Investments | J54: =-(J83-I83) -> -2147.55 | K54: =-(K83-J83) -> -2387.3597 | L54: =-(L83-K83) -> -2639.2674 | M54: =-(M83-L83) -> -2955.0369 | N54: =-(N83-M83) -> -3300.2389
B55: Change in Investments in Long Term Assets | J55: =-(J92-I92) -> -3718.5 | K55: =-(K92-J92) -> -4133.7325 | L55: =-(L92-K92) -> -4569.9125 | M55: =-(M92-L92) -> -5116.6699 | N55: =-(N92-M92) -> -5714.39
B56: Change in Other Non-Current Assets | J56: =-(J93-I93) -> -1080.45 | K56: =-(K93-J93) -> -1201.1002 | L56: =-(L93-K93) -> -1327.837 | M56: =-(M93-L93) -> -1486.7033 | N56: =-(N93-M93) -> -1660.3772
B57: Cash from Investing Activities | J57: =SUM(J52:J56) -> -14812.316 | K57: =SUM(K52:K56) -> -16728.552 | L57: =SUM(L52:L56) -> -18804.267 | M57: =SUM(M52:M56) -> -21237.406 | N57: =SUM(N52:N56) -> -23930.667
B59: CASH FROM FINANCING
B61: Change in Current Debt | J61: =J102-I102 -> 386.85 | K61: =K102-J102 -> 430.04825 | L61: =L102-K102 -> 475.42575 | M61: =M102-L102 -> 532.30705 | N61: =N102-M102 -> 594.49019
B62: Change in Long-Term Debt | J62: =J107-I107 -> -1000 | K62: =K107-J107 -> -1000 | L62: =L107-K107 -> -1000 | M62: =M107-L107 -> -1000 | N62: =N107-M107 -> -1000
B63: Change in Other Non-Current Liabilities | J63: =J108-I108 -> 548.55 | K63: =K108-J108 -> 609.80475 | L63: =L108-K108 -> 674.14966 | M63: =M108-L108 -> 754.80686 | N63: =N108-M108 -> 842.98202
B64: Change in Equity Share Capital | J64: =J112-I112 -> 0 | K64: =K112-J112 -> 0 | L64: =L112-K112 -> 0 | M64: =M112-L112 -> 0 | N64: =N112-M112 -> 0
B65: Dividends Paid | J65: =J233 -> -1971.4587 | K65: =K233 -> -2302.9621 | L65: =L233 -> -2656.8606 | M65: =M233 -> -3041.4013 | N65: =N233 -> -3457.8377
B66: Cash from Financing Activities | J66: =SUM(J61:J65) -> -2036.0587 | K66: =SUM(K61:K65) -> -2263.1091 | L66: =SUM(L61:L65) -> -2507.2852 | M66: =SUM(M61:M65) -> -2754.2874 | N66: =SUM(N61:N65) -> -3020.3655
B68: Beginning Cash Balance | J68: =I70 -> 5941 | K68: =J70 -> 13807.185 | L68: =K70 -> 23334.871 | M68: =L70 -> 34302.981 | N68: =M70 -> 46719.434
B69: Change in Cash | J69: =SUM(J48,J57,J66) -> 7866.1852 | K69: =SUM(K48,K57,K66) -> 9527.6859 | L69: =SUM(L48,L57,L66) -> 10968.11 | M69: =SUM(M48,M57,M66) -> 12416.453 | N69: =SUM(N48,N57,N66) -> 13988.257
B70: Ending Cash Balance | I70: =I82 -> 5941 | J70: =SUM(J68:J69) -> 13807.185 | K70: =SUM(K68:K69) -> 23334.871 | L70: =SUM(L68:L69) -> 34302.981 | M70: =SUM(M68:M69) -> 46719.434 | N70: =SUM(N68:N69) -> 60707.691
B74: Balance Sheet
B76: All figures in INR millions unless stated | H76: 2024 | I76: =H76 + 1 -> 2025 | J76: =I76 + 1 -> 2026 | K76: =J76 + 1 -> 2027 | L76: =K76 + 1 -> 2028 | M76: =L76 + 1 -> 2029 | N76: =M76 + 1 -> 2030
B77: =_xlfn.CONCAT("Model Currently Running:", " ", INDEX(Inputs!$B$15:$B$17, Inputs!$F$8), " ", "Scenario") -> Model Currently Running: Base Case Scenario
B79: ASSETS
B81: Current Assets
B82: Cash and Cash Equivalents | H82: =2761+661 -> 3422 | I82: =2332+3609 -> 5941 | J82: =J70 -> 13807.185 | K82: =K70 -> 23334.871 | L82: =L70 -> 34302.981 | M82: =M70 -> 46719.434 | N82: =N70 -> 60707.691
B83: Short-Term Investments | H83: 6835 | I83: 14317 | J83: =I83*(1+Inputs!H13) -> 16464.55 | K83: =J83*(1+Inputs!I13) -> 18851.91 | L83: =K83*(1+Inputs!J13) -> 21491.177 | M83: =L83*(1+Inputs!K13) -> 24446.214 | N83: =M83*(1+Inputs!L13) -> 27746.453
B84: Accounts Recievables | H84: 8083 | I84: 8148 | J84: =J139 -> 9428.2041 | K84: =K139 -> 10795.294 | L84: =L139 -> 12306.635 | M84: =M139 -> 13998.797 | N84: =N139 -> 15888.635
B85: Inventory | H85: 1187 | I85: 1266 | J85: =J140 -> 1346.8863 | K85: =K140 -> 1557.6067 | L85: =L140 -> 1793.2525 | M85: =M140 -> 2059.823 | N85: =N140 -> 2360.5972
B86: Other Current Assets | H86: =791+13673+878+1882 -> 17224 | I86: =221+1723+1080+2488 -> 5512 | J86: =I86*(1+Inputs!H13) -> 6338.8 | K86: =J86*(1+Inputs!I13) -> 7257.926 | L86: =K86*(1+Inputs!J13) -> 8274.0356 | M86: =L86*(1+Inputs!K13) -> 9411.7155 | N86: =M86*(1+Inputs!L13) -> 10682.297
B87: Total Current Assets | H87: =SUM(H82:H86) -> 36751 | I87: =SUM(I82:I86) -> 35184 | J87: =SUM(J82:J86) -> 47385.626 | K87: =SUM(K82:K86) -> 61797.607 | L87: =SUM(L82:L86) -> 78168.081 | M87: =SUM(M82:M86) -> 96635.983 | N87: =SUM(N82:N86) -> 117385.67
B89: Non-Current Assets
B90: Property, Plant & Equipment | H90: =47096+12612+1725 -> 61433 | I90: =49105+13285+2940 -> 65330 | J90: =J202 -> 63469.668 | K90: =K202 -> 61906.271 | L90: =L202 -> 60640.083 | M90: =M202 -> 59688.33 | N90: =N202 -> 59066.509
B91: Intangible Assets | H91: =608+272 -> 880 | I91: =1091+125 -> 1216 | J91: =I91 -> 1216 | K91: =J91 -> 1216 | L91: =K91 -> 1216 | M91: =L91 -> 1216 | N91: =M91 -> 1216
B92: Investments in Long Term Assets | H92: =19377 -> 19377 | I92: 24790 | J92: =I92*(1+Inputs!H13) -> 28508.5 | K92: =J92*(1+Inputs!I13) -> 32642.232 | L92: =K92*(1+Inputs!J13) -> 37212.145 | M92: =L92*(1+Inputs!K13) -> 42328.815 | N92: =M92*(1+Inputs!L13) -> 48043.205
B93: Other Long Term Financial Assets | H93: =2446+1789+729+647 -> 5611 | I93: =4291+1530+290+1092 -> 7203 | J93: =I93 *(1+ Inputs!H13) -> 8283.45 | K93: =J93 *(1+ Inputs!I13) -> 9484.5502 | L93: =K93 *(1+ Inputs!J13) -> 10812.387 | M93: =L93 *(1+ Inputs!K13) -> 12299.091 | N93: =M93 *(1+ Inputs!L13) -> 13959.468
B94: Total Non-Current Assets | H94: =SUM(H90:H93) -> 87301 | I94: =SUM(I90:I93) -> 98539 | J94: =SUM(J90:J93) -> 101477.62 | K94: =SUM(K90:K93) -> 105249.05 | L94: =SUM(L90:L93) -> 109880.62 | M94: =SUM(M90:M93) -> 115532.24 | N94: =SUM(N90:N93) -> 122285.18
B96: Total Assets | H96: =H87+H94 -> 124052 | I96: =I87+I94 -> 133723 | J96: =J87+J94 -> 148863.24 | K96: =K87+K94 -> 167046.66 | L96: =L87+L94 -> 188048.7 | M96: =M87+M94 -> 212168.22 | N96: =N87+N94 -> 239670.85
B98: LIABILITIES & EQUITY
B100: Current Liabilities
B101: Accounts Payables | H101: =586+6989 -> 7575 | I101: =627+7600 -> 8227 | J101: =J141 -> 9091.4825 | K101: =K141 -> 10513.845 | L101: =L141 -> 12104.454 | M101: =M141 -> 13903.805 | N101: =N141 -> 15934.031
B102: Current Debt | H102: =1702+1098 -> 2800 | I102: =2297+282 -> 2579 | J102: =I102*(1+Inputs!H13) -> 2965.85 | K102: =J102*(1+Inputs!I13) -> 3395.8982 | L102: =K102*(1+Inputs!J13) -> 3871.324 | M102: =L102*(1+Inputs!K13) -> 4403.6311 | N102: =M102*(1+Inputs!L13) -> 4998.1212
B103: Other Current Liabilities | H103: =(1236+1078+1013) -> 3327 | I103: =(1002+1323+1276) -> 3601 | J103: =I103*(1+Inputs!H13) -> 4141.15 | K103: =J103*(1+Inputs!I13) -> 4741.6167 | L103: =K103*(1+Inputs!J13) -> 5405.4431 | M103: =L103*(1+Inputs!K13) -> 6148.6915 | N103: =M103*(1+Inputs!L13) -> 6978.7649
B104: Total Current Liabilities | H104: =SUM(H101:H103) -> 13702 | I104: =SUM(I101:I103) -> 14407 | J104: =SUM(J101:J103) -> 16198.483 | K104: =SUM(K101:K103) -> 18651.36 | L104: =SUM(L101:L103) -> 21381.221 | M104: =SUM(M101:M103) -> 24456.128 | N104: =SUM(N101:N103) -> 27910.917
B106: Non-Current Liabilities
B107: Long Term Debt | H107: =17855+11563 -> 29418 | I107: =15535+12782 -> 28317 | J107: =J213 -> 27317 | K107: =K213 -> 26317 | L107: =L213 -> 25317 | M107: =M213 -> 24317 | N107: =N213 -> 23317
B108: Other Non-Current Liabilities | H108: =23+3764+36 -> 3823 | I108: =12+3632+13 -> 3657 | J108: =I108*(1+Inputs!H13) -> 4205.55 | K108: =J108*(1+Inputs!I13) -> 4815.3547 | L108: =K108*(1+Inputs!J13) -> 5489.5044 | M108: =L108*(1+Inputs!K13) -> 6244.3113 | N108: =M108*(1+Inputs!L13) -> 7087.2933
B109: Total Non-Current Liabilities | H109: =SUM(H107:H108) -> 33241 | I109: =SUM(I107:I108) -> 31974 | J109: =SUM(J107:J108) -> 31522.55 | K109: =SUM(K107:K108) -> 31132.355 | L109: =SUM(L107:L108) -> 30806.504 | M109: =SUM(M107:M108) -> 30561.311 | N109: =SUM(N107:N108) -> 30404.293
B111: Equity
B112: Equity Share Capital | H112: 719 | I112: 719 | J112: =I112 -> 719 | K112: =J112 -> 719 | L112: =K112 -> 719 | M112: =L112 -> 719 | N112: =M112 -> 719
B113: Other Equity | H113: 76390 | I113: 86623 | J113: =J234 -> 100423.21 | K113: =K234 -> 116543.95 | L113: =L234 -> 135141.97 | M113: =M234 -> 156431.78 | N113: =N234 -> 180636.64
B114: Total Shareholders' Equity | H114: =SUM(H112:H113) -> 77109 | I114: =SUM(I112:I113) -> 87342 | J114: =SUM(J112:J113) -> 101142.21 | K114: =SUM(K112:K113) -> 117262.95 | L114: =SUM(L112:L113) -> 135860.97 | M114: =SUM(M112:M113) -> 157150.78 | N114: =SUM(N112:N113) -> 181355.64
B116: Total Liabilities and Equity | H116: =SUM(H104,H109,H114) -> 124052 | I116: =SUM(I104,I109,I114) -> 133723 | J116: =SUM(J104,J109,J114) -> 148863.24 | K116: =SUM(K104,K109,K114) -> 167046.66 | L116: =SUM(L104,L109,L114) -> 188048.7 | M116: =SUM(M104,M109,M114) -> 212168.22 | N116: =SUM(N104,N109,N114) -> 239670.85
B119: Balance Sheet Check | H119: =H96-H116 -> 0 | I119: =I96-I116 -> 0 | J119: =J96-J116 -> 0 | K119: =K96-K116 -> 0 | L119: =L96-L116 -> 0 | M119: =M96-M116 -> 0 | N119: =N96-N116 -> 0
B122: Working Capital Schedule
B124: All figures in INR millions unless stated | H124: 2024 | I124: =H124 + 1 -> 2025 | J124: =I124 + 1 -> 2026 | K124: =J124 + 1 -> 2027 | L124: =K124 + 1 -> 2028 | M124: =L124 + 1 -> 2029 | N124: =M124 + 1 -> 2030
B125: =_xlfn.CONCAT("Model Currently Running:", " ", INDEX(Inputs!$B$15:$B$17, Inputs!$F$8), " ", "Scenario") -> Model Currently Running: Base Case Scenario
B127: Days in Period | H127: 365 | I127: 365 | J127: 365 | K127: 365 | L127: 365 | M127: 365 | N127: 365
B128: Revenue | H128: =H13 -> 74537 | I128: =I13 -> 85498 | J128: =J13 -> 98322.7 | K128: =K13 -> 112579.49 | L128: =L13 -> 128340.62 | M128: =M13 -> 145987.46 | N128: =N13 -> 165695.76
B129: COGS | H129: =-H14 -> 19990 | I129: =-I14 -> 22848 | J129: =-J14 -> 24580.675 | K129: =-K14 -> 28426.322 | L129: =-L14 -> 32726.858 | M129: =-M14 -> 37591.77 | N129: =-N14 -> 43080.898
B132: Amounts Per Day
B133: Accounts Receivable | E133: (Days) | H133: =(H139 / H128) * H127 -> 39.581617 | I133: =(I139 / I128) * I127 -> 34.784673 | J133: =Inputs!H43 -> 35 | K133: =Inputs!I43 -> 35 | L133: =Inputs!J43 -> 35 | M133: =Inputs!K43 -> 35 | N133: =Inputs!L43 -> 35
B134: Inventory | E134: (Days) | H134: =(H140 / H$129) * H$127 -> 21.673587 | I134: =(I140 / I$129) * I$127 -> 20.224527 | J134: =Inputs!H44 -> 20 | K134: =Inputs!I44 -> 20 | L134: =Inputs!J44 -> 20 | M134: =Inputs!K44 -> 20 | N134: =Inputs!L44 -> 20
B135: Accounts Payable | E135: (Days) | H135: =(H141 / H$129) * H$127 -> 138.31291 | I135: =(I141 / I$129) * I$127 -> 131.42748 | J135: =Inputs!H45 -> 135 | K135: =Inputs!I45 -> 135 | L135: =Inputs!J45 -> 135 | M135: =Inputs!K45 -> 135 | N135: =Inputs!L45 -> 135
B138: Total Amounts
B139: Accounts Receivable | H139: =H84 -> 8083 | I139: =I84 -> 8148 | J139: =(J133/J127)*J128 -> 9428.2041 | K139: =(K133/K127)*K128 -> 10795.294 | L139: =(L133/L127)*L128 -> 12306.635 | M139: =(M133/M127)*M128 -> 13998.797 | N139: =(N133/N127)*N128 -> 15888.635
B140: Inventory | H140: =H85 -> 1187 | I140: =I85 -> 1266 | J140: =(J134/J127)*J129 -> 1346.8863 | K140: =(K134/K127)*K129 -> 1557.6067 | L140: =(L134/L127)*L129 -> 1793.2525 | M140: =(M134/M127)*M129 -> 2059.823 | N140: =(N134/N127)*N129 -> 2360.5972
B141: Accounts Payable | H141: =H101 -> 7575 | I141: =I101 -> 8227 | J141: =(J135/J127)*J129 -> 9091.4825 | K141: =(K135/K127)*K129 -> 10513.845 | L141: =(L135/L127)*L129 -> 12104.454 | M141: =(M135/M127)*M129 -> 13903.805 | N141: =(N135/N127)*N129 -> 15934.031
B144: Net Working Capital
B145: Current Assets | H145: =H139 -> 8083 | I145: =I139 -> 8148 | J145: =J139 -> 9428.2041 | K145: =K139 -> 10795.294 | L145: =L139 -> 12306.635 | M145: =M139 -> 13998.797 | N145: =N139 -> 15888.635
B146: Current Liabilities | H146: =SUM(H140:H141) -> 8762 | I146: =SUM(I140:I141) -> 9493 | J146: =SUM(J140:J141) -> 10438.369 | K146: =SUM(K140:K141) -> 12071.452 | L146: =SUM(L140:L141) -> 13897.707 | M146: =SUM(M140:M141) -> 15963.628 | N146: =SUM(N140:N141) -> 18294.628
B147: Net Working Capital | H147: =SUM(H145:H146) -> 16845 | I147: =SUM(I145:I146) -> 17641 | J147: =SUM(J145:J146) -> 19866.573 | K147: =SUM(K145:K146) -> 22866.745 | L147: =SUM(L145:L146) -> 26204.342 | M147: =SUM(M145:M146) -> 29962.425 | N147: =SUM(N145:N146) -> 34183.263
B150: Cash From Working Capital | I150: =I147-H147 -> 796 | J150: =J147-I147 -> 2225.5729 | K150: =K147-J147 -> 3000.1724 | L150: =L147-K147 -> 3337.5964 | M150: =M147-L147 -> 3758.0837 | N150: =N147-M147 -> 4220.8373
B153: Depreciation and Amortization Schedule
...
